VERSION
openpay/__init__.py
openpay/api.py
openpay/error.py
openpay/http_client.py
openpay/resource.py
openpay/util.py
openpay/version.py
openpay/test/__init__.py
openpay/test/helper.py
openpay/test/test_integration.py
openpay/test/test_resources.py
openpay-0.6.dist-info/METADATA
openpay-0.6.dist-info/RECORD
openpay-0.6.dist-info/WHEEL
openpay-0.6.dist-info/top_level.txt
