Metadata-Version: 1.0
Name: openpay
Version: 0.6
Summary: Openpay python bindings
Home-page: https://www.openpay.mx/
Author: Openpay
Author-email: soporte@openpay.mx
License: UNKNOWN
Platform: UNKNOWN
